slack_on/__init__.py
slack_on/dispatcher.py
slack_on-0.0.1.dev1.dist-info/DESCRIPTION.rst
slack_on-0.0.1.dev1.dist-info/METADATA
slack_on-0.0.1.dev1.dist-info/RECORD
slack_on-0.0.1.dev1.dist-info/WHEEL
slack_on-0.0.1.dev1.dist-info/metadata.json
slack_on-0.0.1.dev1.dist-info/top_level.txt
